labelr/__init__.py
labelr/__main__.py
labelr/annotate.py
labelr/check.py
labelr/config.py
labelr/dataset_features.py
labelr/google_genai.py
labelr/main.py
labelr/project_config.py
labelr/types.py
labelr/utils.py
labelr/apps/__init__.py
labelr/apps/datasets.py
labelr/apps/evaluate.py
labelr/apps/google_batch.py
labelr/apps/hugging_face.py
labelr/apps/label_studio.py
labelr/apps/train.py
labelr/evaluate/__init__.py
labelr/evaluate/object_detection.py
labelr/export/__init__.py
labelr/export/classification.py
labelr/export/common.py
labelr/export/llm.py
labelr/export/object_detection.py
labelr/sample/__init__.py
labelr/sample/classification.py
labelr/sample/common.py
labelr/sample/llm.py
labelr/sample/object_detection.py
labelr-0.10.0.dist-info/licenses/LICENSE
labelr-0.10.0.dist-info/METADATA
labelr-0.10.0.dist-info/WHEEL
labelr-0.10.0.dist-info/entry_points.txt
labelr-0.10.0.dist-info/top_level.txt
labelr-0.10.0.dist-info/RECORD
