Metadata-Version: 2.4
Name: labelr
Version: 0.10.0
Summary: A command-line tool to manage labeling tasks with Label Studio.
Requires-Python: >=3.10
License-File: LICENSE
Requires-Dist: datasets>=3.2.0
Requires-Dist: imagehash>=4.3.1
Requires-Dist: label-studio-sdk>=1.0.8
Requires-Dist: more-itertools>=10.5.0
Requires-Dist: openfoodfacts>=2.9.0
Requires-Dist: typer>=0.15.1
Requires-Dist: google-cloud-batch==0.18.0
Requires-Dist: huggingface-hub
Requires-Dist: deepdiff>=8.6.1
Requires-Dist: rapidfuzz>=3.14.3
Requires-Dist: aiohttp
Requires-Dist: aiofiles
Requires-Dist: orjson
Requires-Dist: google-cloud-storage
Requires-Dist: gcloud-aio-storage
Requires-Dist: google-genai>=1.56.0
Provides-Extra: ultralytics
Requires-Dist: ultralytics==8.3.223; extra == "ultralytics"
Provides-Extra: fiftyone
Requires-Dist: fiftyone~=1.10.0; extra == "fiftyone"
Dynamic: license-file
